architecture/def_opcode.v
`ifndef AK16_OPCODE_V
`define AK16_OPCODE_V
//let me define opcodes for ak-16bit

// AK-16b cpu opcodes

//Instruction format:
// [15:12] - Opcode , [11:8] - rd/rs2, [7:4] - rs1, [3:0] - rs2/ imm
//System
`define OPCODE_NOP 4'h0
`define OPCODE_HALT 4'hF

//R-type 
`define OPCODE_ADD 4'h1
`define OPCODE_SUB 4'h2
`define OPCODE_AND 4'h3
`define OPCODE_OR 4'h4
`define OPCODE_XOR 4'h5
`define OPCODE_SLT 4'h6

//I-type
`define OPCODE_ADDI 4'h7
`define OPCODE_ANDI 4'h8
`define OPCODE_ORI 4'h9
`define OPCODE_XORI 4'hA
//Memory
`define OPCODE_LOAD 4'hB
`define OPCODE_STORE 4'hC

//control flow
`define OPCODE_BEQ 4'hD
`define OPCODE_BNE 4'hE
//4'hF is reserved for HALT


//ALU OP defs
`define ALU_ADD 4'h0
`define ALU_SUB 4'h1
`define ALU_AND 4'h2
`define ALU_OR 4'h3
`define ALU_XOR 4'h4
`define ALU_SLT 4'h5
`endif

architecture/dmem.v
module dmem(
    input clk,
    input [15:0] addr,
    input [15:0] wdata,
    input mem_write,
    input mem_read,
    output [15:0] rdata
);

    reg [15:0] mem [0:255];

    always @(posedge clk) begin
        if (mem_write) 
            mem[addr[7:0]] <= wdata;
    end

    assign rdata = mem_read ? mem[addr[7:0]] : 16'd0;

endmodule

architecture/alu.v
`include "def_opcode.v"

module alu(
    input [15:0] a, b,
    input [3:0] alu_op,
    output reg [15:0] alu_result,
    output zero
);

    

    always @(*) begin
        case(alu_op)
            `ALU_ADD: alu_result = a+b ;
            `ALU_SUB: alu_result = a-b;
            `ALU_AND: alu_result = a&b;
            `ALU_OR: alu_result= a |b;
            `ALU_XOR: alu_result = a ^b;
            `ALU_SLT: alu_result = ($signed(a) < $signed(b) ) ? 16'd1 : 16'd0;
            default: alu_result = 16'd0;
        endcase
    end

    assign zero = (alu_result == 16'b0);
endmodule

architecture/regfile.v
module regfile(
    input clk,
    input rst,
    input reg_write,
    input [3:0] rs1,
    input [3:0] rs2,
    input [3:0] rd,
    input [15:0] rd_data,
    output [15:0] rs1_data,
    output [15:0] rs2_data
);

    reg [15:0] regs [0:15];
    integer i;

    // WRITE (synchronous)
    always @(posedge clk or posedge rst) begin
        if (rst) begin
            for (i = 0; i < 16; i = i + 1)
                regs[i] <= 16'd0;
        end else if (reg_write && rd != 0) begin
            regs[rd] <= rd_data;
        end
    end

    assign rs1_data = (rs1 == 4'd0) ? 16'd0 : regs[rs1];
    assign rs2_data = (rs2 == 4'd0) ? 16'd0 : regs[rs2];
    
endmodule

architecture/control.v
`include "def_opcode.v"

module control (
    input [3:0] opcode,
    output reg reg_write ,
    output reg alu_src ,
    output reg mem_read,
    output reg mem_write,
    output reg mem_to_reg,
    output reg branch,
    output reg branch_ne,
    output reg pc_write,
    output reg [3:0] alu_op 
    
);

    always @(*) begin
        // Default values
        reg_write = 0;
        alu_src = 0;
        mem_read=0;
        mem_write=0;
        mem_to_reg=0;
        branch = 0;
        branch_ne =0;
        pc_write = 1;
        alu_op = `ALU_ADD;

        case (opcode)
            `OPCODE_ADD : begin reg_write=1; alu_op=`ALU_ADD; end
            `OPCODE_SUB : begin reg_write=1; alu_op=`ALU_SUB;  end
            `OPCODE_AND : begin reg_write=1; alu_op=`ALU_AND; end
            `OPCODE_OR  : begin reg_write=1; alu_op=`ALU_OR;  end
            `OPCODE_XOR : begin reg_write=1; alu_op=`ALU_XOR; end
            `OPCODE_SLT : begin reg_write=1; alu_op=`ALU_SLT;  end

            `OPCODE_ADDI : begin reg_write=1; alu_op=`ALU_ADD; alu_src=1; end 
            `OPCODE_ANDI : begin reg_write=1; alu_op=`ALU_AND; alu_src=1; end
            `OPCODE_ORI : begin reg_write=1; alu_op=`ALU_OR; alu_src=1; end
            `OPCODE_XORI : begin reg_write=1; alu_op=`ALU_XOR; alu_src=1; end

            `OPCODE_LOAD : begin reg_write=1;  alu_src=1; mem_read=1; mem_to_reg=1; end
            `OPCODE_STORE : begin  alu_src=1; mem_write=1; end
            
            `OPCODE_BEQ : begin branch =1 ; alu_op=`ALU_SUB; alu_src=1; reg_write = 1'b0;end 
            `OPCODE_BNE : begin branch_ne =1 ; alu_op=`ALU_SUB; alu_src=1; reg_write = 1'b0; end

            `OPCODE_HALT : pc_write =0;         
        endcase
    end
endmodule

architecture/imem.v
module imem(
    input  [15:0] addr,
    output [15:0] instr
);

    reg [15:0] mem [0:255];
    integer i;
    initial begin
        // Initialize all memory to NOP
        for (i = 0; i < 256; i = i + 1)
            mem[i] = 16'h0000;
        $readmemh("program.hex", mem);
        
        // Debug: Display loaded instructions
        $display("\n=== Instruction Memory Loaded ===");
        $display("Addr | Instruction");
        $display("-----|------------");
        for (i = 0; i < 20; i = i + 1) begin
            if (mem[i] != 16'h0000)
                $display(" %02h  |    %04h", i, mem[i]);
        end
        $display("========================\n");
    end

    assign instr = mem[addr[7:0]];

endmodule

architecture/pc.v
module pc(
    input clk,
    input rst,
    input pc_write,
    input [15:0] next_pc ,
    output reg [15:0] pc
);

    always @(posedge clk or posedge rst) begin
        if (rst) 
            pc<= 16'd0;
        else if ( pc_write)
            pc<=next_pc;
    end
endmodule

architecture/cpu_top.v
`include "def_opcode.v"

module cpu_top(
    input clk,
    input rst
);

    //program counter wires
    wire [15:0] pc;
    reg [15:0] next_pc;
    wire [15:0] pc_plus_1;
    
    assign pc_plus_1 = pc + 16'd1;
    //instruction 
    wire [15:0] instr;

    wire[3:0] opcode ;
    assign opcode = instr[15:12];
    wire[3:0] rd = instr[11:8];
    wire[3:0] rs1 = instr[7:4];
    wire[3:0] rs2 = instr[3:0];

    wire signed [15:0] imm = {{12{instr[3]}}, instr[3:0]};

    //control signals 
    wire reg_write, alu_src;
    wire mem_read, mem_write, mem_to_reg;
    wire branch, branch_ne, pc_write;
    wire [3:0] alu_op;

    //regfile
    wire [15:0] rs1_data, rs2_data;
    wire [15:0] rd_data;

    //ALU- the undisputed champion
    wire [15:0] alu_b = alu_src ? imm : rs2_data;
    wire [15:0] alu_result;
    wire  zero;
    //data memory
    wire [15:0] mem_out;
    assign rd_data = mem_to_reg ? mem_out : alu_result;
    always @(*) begin
    next_pc = pc + 16'd1;   // default

    // BEQ
    if (opcode == 4'hD && zero) begin
        next_pc = pc + 16'd1 + imm;
    end
    // JUMP
    else if (opcode == 4'h4) begin
        next_pc = imm;
    end
    end



    pc  u_pc(clk,rst, pc_write, next_pc, pc);
    imem u_imem(pc, instr);
    control u_ctrl (.opcode(opcode),
        .reg_write(reg_write),
        .alu_src(alu_src),
        .mem_read(mem_read),
        .mem_write(mem_write),
        .mem_to_reg(mem_to_reg),
        .branch(branch),
        .branch_ne(branch_ne),
        .pc_write(pc_write),
        .alu_op(alu_op)
    );
    
    regfile u_rf(.clk(clk),
        .rst(rst),
        .reg_write(reg_write),
        .rs1(rs1),
        .rs2(rs2),
        .rd(rd),
        .rd_data(rd_data),
        .rs1_data(rs1_data),
        .rs2_data(rs2_data)
    );

    alu u_alu(.a(rs1_data),
        .b(alu_b),
        .alu_op(alu_op),
        .alu_result(alu_result),
        .zero(zero)
    );
    
    dmem u_dmem(
        .clk(clk),
        .mem_write(mem_write),
        .mem_read(mem_read),
        .addr(alu_result),
        .wdata(rs2_data),
        .rdata(mem_out)
    );

    
endmodule

architecture/cpu_tb.v
module cpu_tb;
    reg clk;
    reg rst;

    // Instantiate CPU
    cpu_top dut(
        .clk(clk),
        .rst(rst)
    );

    // Clock generation - 10ns period (100MHz)
    initial begin
        clk = 0;
        forever #5 clk = ~clk;
    end

    // Test sequence
    initial begin
        // Dump waveforms
        $dumpfile("cpu.vcd");
        $dumpvars(0, cpu_tb);

        // Display register values
        $display("\n=== AK-16 CPU Simulation Started ===\n");
        $monitor("T=%0t | PC=%h Instr=%h Op=%h | R1=%h R2=%h R3=%h R4=%h | MemW=%b RegW=%b", 
                 $time, dut.pc, dut.instr, dut.opcode,
                 dut.u_rf.regs[1], dut.u_rf.regs[2], 
                 dut.u_rf.regs[3], dut.u_rf.regs[4],
                 dut.mem_write, dut.reg_write);
        // Reset sequence
        rst = 1;
        #15;
        rst = 0;
        
        // Run for sufficient time
        #500;
        
        // Display final register state
        $display("\n=== Final Register State ===");
        $display("R0=%h R1=%h R2=%h R3=%h", 
                 dut.u_rf.regs[0], dut.u_rf.regs[1],
                 dut.u_rf.regs[2], dut.u_rf.regs[3]);
        $display("R4=%h R5=%h R6=%h R7=%h",
                 dut.u_rf.regs[4], dut.u_rf.regs[5],
                 dut.u_rf.regs[6], dut.u_rf.regs[7]);
        $display("R8=%h R9=%h RA=%h RB=%h",
                 dut.u_rf.regs[8], dut.u_rf.regs[9],
                 dut.u_rf.regs[10], dut.u_rf.regs[11]);
        $display("RC=%h RD=%h RE=%h RF=%h",
                 dut.u_rf.regs[12], dut.u_rf.regs[13],
                 dut.u_rf.regs[14], dut.u_rf.regs[15]);
        
        //to view memory contents
        $display("\n=== Memory Contents ===");
        $display("mem[0]=%h mem[1]=%h mem[2]=%h mem[3]=%h",
                 dut.u_dmem.mem[0], dut.u_dmem.mem[1],
                 dut.u_dmem.mem[2], dut.u_dmem.mem[3]);

        $finish;
    end
    //Watchdog for HALT detection
    always @(posedge clk) begin
        if (dut.instr == 16'hF00 && !rst ) begin
            #20;
            $display("\n=== HALT Instruction Detected at PC=%h===", dut.pc);
            $display("\n=== All Registers (Hex/Dec) ===");
            $display("R0 = %04h (%5d)    R1 = %04h (%5d)", 
                     dut.u_rf.regs[0], dut.u_rf.regs[0],
                     dut.u_rf.regs[1], dut.u_rf.regs[1]);
            $display("R2 = %04h (%5d)    R3 = %04h (%5d)", 
                     dut.u_rf.regs[2], dut.u_rf.regs[2],
                     dut.u_rf.regs[3], dut.u_rf.regs[3]);
            $display("R4 = %04h (%5d)    R5 = %04h (%5d)", 
                     dut.u_rf.regs[4], dut.u_rf.regs[4],
                     dut.u_rf.regs[5], $signed(dut.u_rf.regs[5]));
            $display("R6 = %04h (%5d)    R7 = %04h (%5d)", 
                     dut.u_rf.regs[6], dut.u_rf.regs[6],
                     dut.u_rf.regs[7], dut.u_rf.regs[7]);
            $display("R8 = %04h (%5d)    R9 = %04h (%5d)", 
                     dut.u_rf.regs[8], dut.u_rf.regs[8],
                     dut.u_rf.regs[9], dut.u_rf.regs[9]);
            $display("RA = %04h (%5d)    RB = %04h (%5d)", 
                     dut.u_rf.regs[10], dut.u_rf.regs[10],
                     dut.u_rf.regs[11], dut.u_rf.regs[11]);
            $display("RC = %04h (%5d)    RD = %04h (%5d)", 
                     dut.u_rf.regs[12], dut.u_rf.regs[12],
                     dut.u_rf.regs[13], dut.u_rf.regs[13]);
            $display("RE = %04h (%5d)    RF = %04h (%5d)", 
                     dut.u_rf.regs[14], dut.u_rf.regs[14],
                     dut.u_rf.regs[15], dut.u_rf.regs[15]);
            #10;
            $finish;
        end
    end
endmodule

architecture/cpu.vcd
$date
	Tue Dec 16 23:00:06 2025
$end
$version
	Icarus Verilog
$end
$timescale
	1s
$end
$scope module cpu_tb $end
$var reg 1 ! clk $end
$var reg 1 " rst $end
$scope module dut $end
$var wire 1 ! clk $end
$var wire 1 " rst $end
$var wire 1 # zero $end
$var wire 16 $ rs2_data [15:0] $end
$var wire 4 % rs2 [3:0] $end
$var wire 16 & rs1_data [15:0] $end
$var wire 4 ' rs1 [3:0] $end
$var wire 1 ( reg_write $end
$var wire 16 ) rd_data [15:0] $end
$var wire 4 * rd [3:0] $end
$var wire 1 + pc_write $end
$var wire 16 , pc_plus_1 [15:0] $end
$var wire 16 - pc [15:0] $end
$var wire 4 . opcode [3:0] $end
$var wire 1 / mem_write $end
$var wire 1 0 mem_to_reg $end
$var wire 1 1 mem_read $end
$var wire 16 2 mem_out [15:0] $end
$var wire 16 3 instr [15:0] $end
$var wire 16 4 imm [15:0] $end
$var wire 1 5 branch_ne $end
$var wire 1 6 branch $end
$var wire 1 7 alu_src $end
$var wire 16 8 alu_result [15:0] $end
$var wire 4 9 alu_op [3:0] $end
$var wire 16 : alu_b [15:0] $end
$var reg 16 ; next_pc [15:0] $end
$scope module u_alu $end
$var wire 16 < b [15:0] $end
$var wire 1 # zero $end
$var wire 4 = alu_op [3:0] $end
$var wire 16 > a [15:0] $end
$var reg 16 ? alu_result [15:0] $end
$upscope $end
$scope module u_ctrl $end
$var wire 4 @ opcode [3:0] $end
$var reg 4 A alu_op [3:0] $end
$var reg 1 7 alu_src $end
$var reg 1 6 branch $end
$var reg 1 5 branch_ne $end
$var reg 1 1 mem_read $end
$var reg 1 0 mem_to_reg $end
$var reg 1 / mem_write $end
$var reg 1 + pc_write $end
$var reg 1 ( reg_write $end
$upscope $end
$scope module u_dmem $end
$var wire 16 B addr [15:0] $end
$var wire 1 ! clk $end
$var wire 1 1 mem_read $end
$var wire 1 / mem_write $end
$var wire 16 C wdata [15:0] $end
$var wire 16 D rdata [15:0] $end
$upscope $end
$scope module u_imem $end
$var wire 16 E instr [15:0] $end
$var wire 16 F addr [15:0] $end
$var integer 32 G i [31:0] $end
$upscope $end
$scope module u_pc $end
$var wire 1 ! clk $end
$var wire 16 H next_pc [15:0] $end
$var wire 1 + pc_write $end
$var wire 1 " rst $end
$var reg 16 I pc [15:0] $end
$upscope $end
$scope module u_rf $end
$var wire 1 ! clk $end
$var wire 4 J rd [3:0] $end
$var wire 16 K rd_data [15:0] $end
$var wire 1 ( reg_write $end
$var wire 4 L rs1 [3:0] $end
$var wire 4 M rs2 [3:0] $end
$var wire 1 " rst $end
$var wire 16 N rs2_data [15:0] $end
$var wire 16 O rs1_data [15:0] $end
$var integer 32 P i [31:0] $end
$upscope $end
$upscope $end
$upscope $end
$enddefinitions $end
$comment Show the parameter values. $end
$dumpall
$end
#0
$dumpvars
b10000 P
b0 O
b0 N
b1 M
b0 L
b1 K
b1 J
b0 I
b1 H
b10100 G
b0 F
b111000100000001 E
b0 D
b0 C
b1 B
b0 A
b111 @
b1 ?
b0 >
b0 =
b1 <
b1 ;
b1 :
b0 9
b1 8
17
06
05
b1 4
b111000100000001 3
b0 2
01
00
0/
b111 .
b0 -
b1 ,
1+
b1 *
b1 )
1(
b0 '
b0 &
b1 %
b0 $
0#
1"
0!
$end
#5
b10000 P
1!
#10
0!
#15
b0 )
b0 K
1#
b0 8
b0 ?
b0 B
b0 :
b0 <
b0 4
b0 %
b0 M
b10 *
b10 J
b111001000000000 3
b111001000000000 E
b10 ;
b10 H
b0 $
b0 C
b0 N
b10 ,
b1 -
b1 F
b1 I
1!
0"
#20
0!
#25
b111 )
b111 K
0#
b111 8
b111 ?
b111 B
b111 :
b111 <
b111 4
b111 %
b111 M
b11 *
b11 J
b111001100000111 3
b111001100000111 E
b11 ;
b11 H
b11 ,
b10 -
b10 F
b10 I
1!
#30
0!
#35
b101 )
b101 K
b101 8
b101 ?
b101 B
b10 :
b10 <
b111 &
b111 >
b111 O
b1 9
b1 =
b1 A
16
17
0(
b10 4
b10 %
b10 M
b11 '
b11 L
b10 *
b10 J
b1101 .
b1101 @
b1101001000110010 3
b1101001000110010 E
b100 ;
b100 H
b100 ,
b11 -
b11 F
b11 I
1!
#40
0!
#45
b1 )
b1 K
b1 8
b1 ?
b1 B
b0 :
b0 <
b1 &
b1 >
b1 O
1(
b0 9
b0 =
b0 A
06
07
b1 '
b1 L
b1 *
b1 J
b1 .
b1 @
b1000100010010 3
b1000100010010 E
b101 ;
b101 H
b101 ,
b100 -
b100 F
b100 I
1!
#50
0!
#55
b1 :
b1 <
b1 $
b1 C
b1 N
b0 &
b0 >
b0 O
17
1(
b1 4
b1 %
b1 M
b10 '
b10 L
b10 *
b10 J
b111 .
b111 @
b111001000100001 3
b111001000100001 E
b110 ;
b110 H
b110 ,
b101 -
b101 F
b101 I
1!
#60
0!
#65
b111 )
b111 K
b111 :
b111 <
b111 $
b111 C
b111 N
b11 9
b11 =
b11 A
07
1(
b111 8
b111 ?
b111 B
b11 4
b11 %
b11 M
b0 '
b0 L
b0 *
b0 J
b100 .
b100 @
b0 &
b0 >
b0 O
b100000000000011 3
b100000000000011 E
b11 ;
b11 H
b111 ,
b110 -
b110 F
b110 I
1!
#70
0!
#75
b101 )
b101 K
b10 :
b10 <
0#
b101 8
b101 ?
b101 B
b1 $
b1 C
b1 N
b111 &
b111 >
b111 O
17
16
b1 9
b1 =
b1 A
0(
b10 4
b10 %
b10 M
b11 '
b11 L
b10 *
b10 J
b1101 .
b1101 @
b1101001000110010 3
b1101001000110010 E
b100 ;
b100 H
b100 ,
b11 -
b11 F
b11 I
1!
#80
0!
#85
b10 )
b10 K
b10 8
b10 ?
b10 B
b1 :
b1 <
b1 &
b1 >
b1 O
1(
b0 9
b0 =
b0 A
06
07
b1 '
b1 L
b1 *
b1 J
b1 .
b1 @
b1000100010010 3
b1000100010010 E
b101 ;
b101 H
b101 ,
b100 -
b100 F
b100 I
1!
#90
0!
#95
b10 $
b10 C
b10 N
17
1(
b10 )
b10 K
b1 4
b1 %
b1 M
b10 '
b10 L
b10 *
b10 J
b111 .
b111 @
b10 8
b10 ?
b10 B
b111001000100001 3
b111001000100001 E
b110 ;
b110 H
b1 &
b1 >
b1 O
b110 ,
b101 -
b101 F
b101 I
1!
#100
0!
#105
b111 )
b111 K
b111 :
b111 <
b111 $
b111 C
b111 N
b11 9
b11 =
b11 A
07
1(
b111 8
b111 ?
b111 B
b11 4
b11 %
b11 M
b0 '
b0 L
b0 *
b0 J
b100 .
b100 @
b0 &
b0 >
b0 O
b100000000000011 3
b100000000000011 E
b11 ;
b11 H
b111 ,
b110 -
b110 F
b110 I
1!
#110
0!
#115
b101 )
b101 K
b10 :
b10 <
0#
b101 8
b101 ?
b101 B
b10 $
b10 C
b10 N
b111 &
b111 >
b111 O
17
16
b1 9
b1 =
b1 A
0(
b10 4
b10 %
b10 M
b11 '
b11 L
b10 *
b10 J
b1101 .
b1101 @
b1101001000110010 3
b1101001000110010 E
b100 ;
b100 H
b100 ,
b11 -
b11 F
b11 I
1!
#120
0!
#125
b100 )
b100 K
b100 8
b100 ?
b100 B
b10 &
b10 >
b10 O
1(
b0 9
b0 =
b0 A
06
07
b1 '
b1 L
b1 *
b1 J
b1 .
b1 @
b1000100010010 3
b1000100010010 E
b101 ;
b101 H
b101 ,
b100 -
b100 F
b100 I
1!
#130
0!
#135
b1 :
b1 <
b100 $
b100 C
b100 N
17
1(
b11 )
b11 K
b1 4
b1 %
b1 M
b10 '
b10 L
b10 *
b10 J
b111 .
b111 @
b11 8
b11 ?
b11 B
b111001000100001 3
b111001000100001 E
b110 ;
b110 H
b10 &
b10 >
b10 O
b110 ,
b101 -
b101 F
b101 I
1!
#140
0!
#145
b111 )
b111 K
b111 :
b111 <
b111 $
b111 C
b111 N
b11 9
b11 =
b11 A
07
1(
b111 8
b111 ?
b111 B
b11 4
b11 %
b11 M
b0 '
b0 L
b0 *
b0 J
b100 .
b100 @
b0 &
b0 >
b0 O
b100000000000011 3
b100000000000011 E
b11 ;
b11 H
b111 ,
b110 -
b110 F
b110 I
1!
#150
0!
#155
b101 )
b101 K
b10 :
b10 <
0#
b101 8
b101 ?
b101 B
b11 $
b11 C
b11 N
b111 &
b111 >
b111 O
17
16
b1 9
b1 =
b1 A
0(
b10 4
b10 %
b10 M
b11 '
b11 L
b10 *
b10 J
b1101 .
b1101 @
b1101001000110010 3
b1101001000110010 E
b100 ;
b100 H
b100 ,
b11 -
b11 F
b11 I
1!
#160
0!
#165
b111 )
b111 K
b111 8
b111 ?
b111 B
b11 :
b11 <
b100 &
b100 >
b100 O
1(
b0 9
b0 =
b0 A
06
07
b1 '
b1 L
b1 *
b1 J
b1 .
b1 @
b1000100010010 3
b1000100010010 E
b101 ;
b101 H
b101 ,
b100 -
b100 F
b100 I
1!
#170
0!
#175
b1 :
b1 <
b111 $
b111 C
b111 N
17
1(
b100 )
b100 K
b1 4
b1 %
b1 M
b10 '
b10 L
b10 *
b10 J
b111 .
b111 @
b100 8
b100 ?
b100 B
b111001000100001 3
b111001000100001 E
b110 ;
b110 H
b11 &
b11 >
b11 O
b110 ,
b101 -
b101 F
b101 I
1!
#180
0!
#185
b111 )
b111 K
b111 :
b111 <
b11 9
b11 =
b11 A
07
1(
b111 8
b111 ?
b111 B
b11 4
b11 %
b11 M
b0 '
b0 L
b0 *
b0 J
b100 .
b100 @
b0 &
b0 >
b0 O
b100000000000011 3
b100000000000011 E
b11 ;
b11 H
b111 ,
b110 -
b110 F
b110 I
1!
#190
0!
#195
b101 )
b101 K
b10 :
b10 <
0#
b101 8
b101 ?
b101 B
b100 $
b100 C
b100 N
b111 &
b111 >
b111 O
17
16
b1 9
b1 =
b1 A
0(
b10 4
b10 %
b10 M
b11 '
b11 L
b10 *
b10 J
b1101 .
b1101 @
b1101001000110010 3
b1101001000110010 E
b100 ;
b100 H
b100 ,
b11 -
b11 F
b11 I
1!
#200
0!
#205
b1011 )
b1011 K
b1011 8
b1011 ?
b1011 B
b100 :
b100 <
1(
b0 9
b0 =
b0 A
06
07
b1 '
b1 L
b1 *
b1 J
b1 .
b1 @
b1000100010010 3
b1000100010010 E
b101 ;
b101 H
b101 ,
b100 -
b100 F
b100 I
1!
#210
0!
#215
b1 :
b1 <
b1011 $
b1011 C
b1011 N
17
1(
b101 )
b101 K
b1 4
b1 %
b1 M
b10 '
b10 L
b10 *
b10 J
b111 .
b111 @
b101 8
b101 ?
b101 B
b111001000100001 3
b111001000100001 E
b110 ;
b110 H
b100 &
b100 >
b100 O
b110 ,
b101 -
b101 F
b101 I
1!
#220
0!
#225
b111 )
b111 K
b111 :
b111 <
b111 $
b111 C
b111 N
b11 9
b11 =
b11 A
07
1(
b111 8
b111 ?
b111 B
b11 4
b11 %
b11 M
b0 '
b0 L
b0 *
b0 J
b100 .
b100 @
b0 &
b0 >
b0 O
b100000000000011 3
b100000000000011 E
b11 ;
b11 H
b111 ,
b110 -
b110 F
b110 I
1!
#230
0!
#235
b101 )
b101 K
b10 :
b10 <
0#
b101 8
b101 ?
b101 B
b101 $
b101 C
b101 N
b111 &
b111 >
b111 O
17
16
b1 9
b1 =
b1 A
0(
b10 4
b10 %
b10 M
b11 '
b11 L
b10 *
b10 J
b1101 .
b1101 @
b1101001000110010 3
b1101001000110010 E
b100 ;
b100 H
b100 ,
b11 -
b11 F
b11 I
1!
#240
0!
#245
b10000 )
b10000 K
b10000 8
b10000 ?
b10000 B
b101 :
b101 <
b1011 &
b1011 >
b1011 O
1(
b0 9
b0 =
b0 A
06
07
b1 '
b1 L
b1 *
b1 J
b1 .
b1 @
b1000100010010 3
b1000100010010 E
b101 ;
b101 H
b101 ,
b100 -
b100 F
b100 I
1!
#250
0!
#255
b1 :
b1 <
b10000 $
b10000 C
b10000 N
17
1(
b110 )
b110 K
b1 4
b1 %
b1 M
b10 '
b10 L
b10 *
b10 J
b111 .
b111 @
b110 8
b110 ?
b110 B
b111001000100001 3
b111001000100001 E
b110 ;
b110 H
b101 &
b101 >
b101 O
b110 ,
b101 -
b101 F
b101 I
1!
#260
0!
#265
b111 )
b111 K
b111 :
b111 <
b111 $
b111 C
b111 N
b11 9
b11 =
b11 A
07
1(
b111 8
b111 ?
b111 B
b11 4
b11 %
b11 M
b0 '
b0 L
b0 *
b0 J
b100 .
b100 @
b0 &
b0 >
b0 O
b100000000000011 3
b100000000000011 E
b11 ;
b11 H
b111 ,
b110 -
b110 F
b110 I
1!
#270
0!
#275
b101 )
b101 K
b10 :
b10 <
0#
b101 8
b101 ?
b101 B
b110 $
b110 C
b110 N
b111 &
b111 >
b111 O
17
16
b1 9
b1 =
b1 A
0(
b10 4
b10 %
b10 M
b11 '
b11 L
b10 *
b10 J
b1101 .
b1101 @
b1101001000110010 3
b1101001000110010 E
b100 ;
b100 H
b100 ,
b11 -
b11 F
b11 I
1!
#280
0!
#285
b10110 )
b10110 K
b10110 8
b10110 ?
b10110 B
b110 :
b110 <
b10000 &
b10000 >
b10000 O
1(
b0 9
b0 =
b0 A
06
07
b1 '
b1 L
b1 *
b1 J
b1 .
b1 @
b1000100010010 3
b1000100010010 E
b101 ;
b101 H
b101 ,
b100 -
b100 F
b100 I
1!
#290
0!
#295
b1 :
b1 <
b10110 $
b10110 C
b10110 N
17
1(
b111 )
b111 K
b1 4
b1 %
b1 M
b10 '
b10 L
b10 *
b10 J
b111 .
b111 @
b111 8
b111 ?
b111 B
b111001000100001 3
b111001000100001 E
b110 ;
b110 H
b110 &
b110 >
b110 O
b110 ,
b101 -
b101 F
b101 I
1!
#300
0!
#305
b111 )
b111 K
b111 :
b111 <
b111 $
b111 C
b111 N
b11 9
b11 =
b11 A
07
1(
b111 8
b111 ?
b111 B
b11 4
b11 %
b11 M
b0 '
b0 L
b0 *
b0 J
b100 .
b100 @
b0 &
b0 >
b0 O
b100000000000011 3
b100000000000011 E
b11 ;
b11 H
b111 ,
b110 -
b110 F
b110 I
1!
#310
0!
#315
b101 )
b101 K
b10 :
b10 <
0#
b101 8
b101 ?
b101 B
b111 &
b111 >
b111 O
17
16
b1 9
b1 =
b1 A
0(
b10 4
b10 %
b10 M
b11 '
b11 L
b10 *
b10 J
b1101 .
b1101 @
b1101001000110010 3
b1101001000110010 E
b100 ;
b100 H
b100 ,
b11 -
b11 F
b11 I
1!
#320
0!
#325
b11101 )
b11101 K
b11101 8
b11101 ?
b11101 B
b111 :
b111 <
b10110 &
b10110 >
b10110 O
1(
b0 9
b0 =
b0 A
06
07
b1 '
b1 L
b1 *
b1 J
b1 .
b1 @
b1000100010010 3
b1000100010010 E
b101 ;
b101 H
b101 ,
b100 -
b100 F
b100 I
1!
#330
0!
#335
b1 :
b1 <
b11101 $
b11101 C
b11101 N
17
1(
b1000 )
b1000 K
b1 4
b1 %
b1 M
b10 '
b10 L
b10 *
b10 J
b111 .
b111 @
b1000 8
b1000 ?
b1000 B
b111001000100001 3
b111001000100001 E
b110 ;
b110 H
b111 &
b111 >
b111 O
b110 ,
b101 -
b101 F
b101 I
1!
#340
0!
#345
b111 )
b111 K
b111 :
b111 <
b111 $
b111 C
b111 N
b11 9
b11 =
b11 A
07
1(
b111 8
b111 ?
b111 B
b11 4
b11 %
b11 M
b0 '
b0 L
b0 *
b0 J
b100 .
b100 @
b0 &
b0 >
b0 O
b100000000000011 3
b100000000000011 E
b11 ;
b11 H
b111 ,
b110 -
b110 F
b110 I
1!
#350
0!
#355
b101 )
b101 K
b10 :
b10 <
0#
b101 8
b101 ?
b101 B
b1000 $
b1000 C
b1000 N
b111 &
b111 >
b111 O
17
16
b1 9
b1 =
b1 A
0(
b10 4
b10 %
b10 M
b11 '
b11 L
b10 *
b10 J
b1101 .
b1101 @
b1101001000110010 3
b1101001000110010 E
b100 ;
b100 H
b100 ,
b11 -
b11 F
b11 I
1!
#360
0!
#365
b100101 )
b100101 K
b100101 8
b100101 ?
b100101 B
b1000 :
b1000 <
b11101 &
b11101 >
b11101 O
1(
b0 9
b0 =
b0 A
06
07
b1 '
b1 L
b1 *
b1 J
b1 .
b1 @
b1000100010010 3
b1000100010010 E
b101 ;
b101 H
b101 ,
b100 -
b100 F
b100 I
1!
#370
0!
#375
b1 :
b1 <
b100101 $
b100101 C
b100101 N
17
1(
b1001 )
b1001 K
b1 4
b1 %
b1 M
b10 '
b10 L
b10 *
b10 J
b111 .
b111 @
b1001 8
b1001 ?
b1001 B
b111001000100001 3
b111001000100001 E
b110 ;
b110 H
b1000 &
b1000 >
b1000 O
b110 ,
b101 -
b101 F
b101 I
1!
#380
0!
#385
b111 )
b111 K
b111 :
b111 <
b111 $
b111 C
b111 N
b11 9
b11 =
b11 A
07
1(
b111 8
b111 ?
b111 B
b11 4
b11 %
b11 M
b0 '
b0 L
b0 *
b0 J
b100 .
b100 @
b0 &
b0 >
b0 O
b100000000000011 3
b100000000000011 E
b11 ;
b11 H
b111 ,
b110 -
b110 F
b110 I
1!
#390
0!
#395
b101 )
b101 K
b10 :
b10 <
0#
b101 8
b101 ?
b101 B
b1001 $
b1001 C
b1001 N
b111 &
b111 >
b111 O
17
16
b1 9
b1 =
b1 A
0(
b10 4
b10 %
b10 M
b11 '
b11 L
b10 *
b10 J
b1101 .
b1101 @
b1101001000110010 3
b1101001000110010 E
b100 ;
b100 H
b100 ,
b11 -
b11 F
b11 I
1!
#400
0!
#405
b101110 )
b101110 K
b101110 8
b101110 ?
b101110 B
b1001 :
b1001 <
b100101 &
b100101 >
b100101 O
1(
b0 9
b0 =
b0 A
06
07
b1 '
b1 L
b1 *
b1 J
b1 .
b1 @
b1000100010010 3
b1000100010010 E
b101 ;
b101 H
b101 ,
b100 -
b100 F
b100 I
1!
#410
0!
#415
b1 :
b1 <
b101110 $
b101110 C
b101110 N
17
1(
b1010 )
b1010 K
b1 4
b1 %
b1 M
b10 '
b10 L
b10 *
b10 J
b111 .
b111 @
b1010 8
b1010 ?
b1010 B
b111001000100001 3
b111001000100001 E
b110 ;
b110 H
b1001 &
b1001 >
b1001 O
b110 ,
b101 -
b101 F
b101 I
1!
#420
0!
#425
b111 )
b111 K
b111 :
b111 <
b111 $
b111 C
b111 N
b11 9
b11 =
b11 A
07
1(
b111 8
b111 ?
b111 B
b11 4
b11 %
b11 M
b0 '
b0 L
b0 *
b0 J
b100 .
b100 @
b0 &
b0 >
b0 O
b100000000000011 3
b100000000000011 E
b11 ;
b11 H
b111 ,
b110 -
b110 F
b110 I
1!
#430
0!
