architecture/def_opcode.v
`ifndef AK16_OPCODE_V
`define AK16_OPCODE_V
//let me define opcodes for ak-16bit

// AK-16b cpu opcodes

//Instruction format:
// [15:12] - Opcode , [11:8] - rd/rs2, [7:4] - rs1, [3:0] - rs2/ imm
//System
`define OPCODE_NOP 4'h0
`define OPCODE_HALT 4'hF

//R-type 
`define OPCODE_ADD 4'h1
`define OPCODE_SUB 4'h2
`define OPCODE_AND 4'h3
`define OPCODE_OR 4'h4
`define OPCODE_XOR 4'h5
`define OPCODE_SLT 4'h6

//I-type
`define OPCODE_ADDI 4'h7
`define OPCODE_ANDI 4'h8
`define OPCODE_ORI 4'h9
`define OPCODE_XORI 4'hA
//Memory
`define OPCODE_LOAD 4'hB
`define OPCODE_STORE 4'hC

//control flow
`define OPCODE_BEQ 4'hD
`define OPCODE_BNE 4'hE
//4'hF is reserved for HALT


//ALU OP defs
`define ALU_ADD 4'h0
`define ALU_SUB 4'h1
`define ALU_AND 4'h2
`define ALU_OR 4'h3
`define ALU_XOR 4'h4
`define ALU_SLT 4'h5
`endif

dmem.v
module dmem(
    input clk,
    input [7:0] addr,
    input [15:0] write_data,
    input mem_write,
    input mem_read,
    output [15:0] read_data
);

    reg [15:0] memory[0:255];
    integer i;
    initial begin
        
        for (i=0; i<256; i=i+1)
            memory[i] = 16'd0;
    end

    assign read_data = mem_read ? memory[addr] : 16'b0;

    always @(posedge clk) begin
        if (mem_write) 
            memory[addr] <= write_data;
    end
endmodule

alu.v
module alu(
    input [15:0] a, b,
    input [3:0] alu_control,
    output reg [15:0] alu_result,
    output zero
);

    

    always @(*) begin
        case(alu_control)
            4'h0: alu_result = a+b ;
            4'h1: alu_result = a-b;
            4'h2: alu_result = a&b;
            4'h3: alu_result= a |b;
            4'h4: alu_result = a ^b;
            4'h5: alu_result = (a < b ) ? 16'd1 : 16'd0;
            default: alu_result = 16'd0;
        endcase
    end

    assign zero = (alu_result == 16'b0);
endmodule

architecture/regfile.v
module regfile(
    input clk,
    input rst,
    input reg_write,
    input [3:0] rs1,
    input [3:0] rs2,
    input [3:0] rd,
    input [15:0] rd_data,
    output [15:0] rs1_data,
    output [15:0] rs2_data
);

    reg [15:0] regs [0:15];
    integer i;

    // WRITE (synchronous)
    always @(posedge clk or posedge rst) begin
        if (rst) begin
            for (i = 0; i < 16; i = i + 1)
                regs[i] <= 16'd0;
        end else if (reg_write && rd != 0) begin
            regs[rd] <= rd_data;
        end
    end

    assign rs1_data = (rs1 == 4'd0) ? 16'd0 : regs[rs1];
    assign rs2_data = (rs2 == 4'd0) ? 16'd0 : regs[rs2];
    
endmodule

architecture/control.v
`include "def_opcode.v"

module control (
    input [3:0] opcode,
    output reg reg_write ,
    output reg alu_src ,
    output reg [3:0] alu_op ,
    output reg mem_read,
    output reg mem_write,
    output reg mem_to_reg
);

    always @(*) begin
        // Default values
        reg_write = 0;
        alu_src = 0;
        mem_read=0;
        mem_write=0;
        mem_to_reg=0;
        alu_op = `ALU_ADD;

        case (opcode)
            `OPCODE_ADD : begin reg_write=1; alu_op=`ALU_ADD; end
            `OPCODE_SUB : begin reg_write=1; alu_op=`ALU_SUB;  end
            `OPCODE_AND : begin reg_write=1; alu_op=`ALU_AND; end
            `OPCODE_OR  : begin reg_write=1; alu_op=`ALU_OR;  end
            `OPCODE_XOR : begin reg_write=1; alu_op=`ALU_XOR; end
            `OPCODE_SLT : begin reg_write=1; alu_op=`ALU_SLT;  end
            `OPCODE_ADDI : begin reg_write=1; alu_op=`ALU_ADD; alu_src=1; end 
            `OPCODE_ANDI : begin reg_write=1; alu_op=`ALU_AND; alu_src=1; end
            `OPCODE_ORI : begin reg_write=1; alu_op=`ALU_OR; alu_src=1; end
            `OPCODE_XORI : begin reg_write=1; alu_op=`ALU_XOR; alu_src=1; end
            `OPCODE_LW : begin reg_write=1; alu_op=`ALU_ADD; alu_src=1; mem_read=1; mem_to_reg=1; end
            `OPCODE_SW : begin alu_op=`ALU_ADD; alu_src=1; mem_write=1; end
            default : begin 
                // For other opcodes like BEQ, BNE, J, JAL
                reg_write = 0; 
                alu_src = 0; 
                alu_op = `ALU_ADD; 
            end
            
        endcase
    end
endmodule

architecture/imem.v
module imem(
    input  [7:0] addr,
    output [15:0] instr
);

    reg [15:0] mem [0:255];
    integer i;
    initial begin
        
        for (i=0; i<256; i=i+1)
            mem[i] = 16'd0;
        $readmemh("program.hex", mem);
    end

    assign instr = mem[addr];

endmodule

pc.v
module pc(
    input clk,
    input rst,
    input [7:0] next_pc ,
    output reg [7:0] pc
);

    always @(posedge clk or posedge rst) begin
        if (rst) 
            pc<= 8'd0;
        else
            pc<=next_pc;
    end
endmodule

architecture/cpu_top.v
`include "def_opcode.v"

module cpu_top(
    input clk,
    input rst
);

    //program counter wires
    wire [7:0] pc;
    wire [7:0] next_pc = pc+1;

    //instruction 
    wire [15:0] instr;

    //control signals 
    wire reg_write, alu_src;
    wire mem_read, mem_write, mem_to_reg;
    wire [3:0] alu_op;

    //regfile
    wire [15:0] rs1_data, rs2_data;
    wire [3:0] rs1_sel, rs2_sel, rd_sel;

    //ALU- the undisputed champion
    wire [15:0] alu_b;
    wire [15:0] alu_result;
    wire  zero;
    //dta memory
    wire [15:0] mem_read_data;
    wire [15:0] write_back_data;

    assign rs1_sel  = (instr[15:12] == `OPCODE_ADDI ||
                       instr[15:12] == `OPCODE_ANDI ||
                       instr[15:12] == `OPCODE_ORI  ||
                       instr[15:12] == `OPCODE_XORI ||
                       instr[15:12] == `OPCODE_LW   ||
                       instr[15:12] == `OPCODE_SW ) ? instr[7:4] : instr[11:8];

    assign rs2_sel = instr[7:4];

    assign rd_sel  = (instr[15:12] == `OPCODE_ADDI ||
                       instr[15:12] == `OPCODE_ANDI ||
                       instr[15:12] == `OPCODE_ORI  ||
                       instr[15:12] == `OPCODE_XORI ||
                       instr[15:12] == `OPCODE_LW ) ? instr[11:8] : instr[3:0];

    //pc
    pc pc0(.clk(clk), .rst(rst), .next_pc(next_pc), .pc(pc));
    
    //intruction memory
    imem imem0(.addr(pc), .instr(instr));
    
    
    //control unit - acknowledge me 
    control cu(
        .opcode(instr[15:12]),
        .reg_write(reg_write),
        .alu_src(alu_src),
        .alu_op(alu_op),
        .mem_read(mem_read),
        .mem_write(mem_write),
        .mem_to_reg(mem_to_reg)
    );
    
    // register file
    regfile rf(
        .clk(clk),
        .rst(rst),
        .reg_write(reg_write),
        .rs1(rs1_sel),
        .rs2(rs2_sel),
        .rd(rd_sel),
        .rd_data(write_back_data),
        .rs1_data(rs1_data),
        .rs2_data(rs2_data)
    );

    //ALU input mux
    assign alu_b = alu_src ? { 12'b0, instr[3:0]} : rs2_data;

    //ALU
    alu alu0(
        .a(rs1_data),
        .b(alu_b),
        .alu_control(alu_op),
        .alu_result(alu_result),
        .zero(zero)
    );

    dmem dmem0(
        .clk(clk),
        .addr(alu_result[7:0]) ,
        .write_data(rs2_data),
        .mem_write(mem_write),
        .mem_read(mem_read),
        .read_data(mem_read_data)
    );

    assign write_back_data = mem_to_reg ? mem_read_data : alu_result ;
    
endmodule

architecture/cpu_tb.v
module cpu_tb;
    reg clk;
    reg rst;

    // Instantiate CPU
    cpu_top dut(
        .clk(clk),
        .rst(rst)
    );

    // Clock generation - 10ns period (100MHz)
    initial begin
        clk = 0;
        forever #5 clk = ~clk;
    end

    // Test sequence
    initial begin
        // Dump waveforms
        $dumpfile("cpu.vcd");
        $dumpvars(0, cpu_tb);

        // Display register values
        $display("\n=== AK-16 CPU Simulation Started ===\n");
        $monitor("T=%0t | PC=%h Instr=%h Op=%h | R1=%h R2=%h R3=%h R4=%h | MemW=%b RegW=%b", 
                 $time, dut.pc, dut.instr, dut.opcode,
                 dut.u_rf.regs[1], dut.u_rf.regs[2], 
                 dut.u_rf.regs[3], dut.u_rf.regs[4],
                 dut.mem_write, dut.reg_write);
        // Reset sequence
        rst = 1;
        #15;
        rst = 0;
        
        // Run for sufficient time
        #500;
        
        // Display final register state
        $display("\n=== Final Register State ===");
        $display("R0=%h R1=%h R2=%h R3=%h", 
                 dut.u_rf.regs[0], dut.u_rf.regs[1],
                 dut.u_rf.regs[2], dut.u_rf.regs[3]);
        $display("R4=%h R5=%h R6=%h R7=%h",
                 dut.u_rf.regs[4], dut.u_rf.regs[5],
                 dut.u_rf.regs[6], dut.u_rf.regs[7]);
        $display("R8=%h R9=%h RA=%h RB=%h",
                 dut.u_rf.regs[8], dut.u_rf.regs[9],
                 dut.u_rf.regs[10], dut.u_rf.regs[11]);
        $display("RC=%h RD=%h RE=%h RF=%h",
                 dut.u_rf.regs[12], dut.u_rf.regs[13],
                 dut.u_rf.regs[14], dut.u_rf.regs[15]);
        
        //to view memory contents
        $display("\n=== Memory Contents ===");
        $display("mem[0]=%h mem[1]=%h mem[2]=%h mem[3]=%h",
                 dut.u_dmem.mem[0], dut.u_dmem.mem[1],
                 dut.u_dmem.mem[2], dut.u_dmem.mem[3]);

        $finish;
    end
    //Watchdog for HALT detection
    always @(posedge clk) begin
        if (dut.instr == 16'hF00 && !rst ) begin
            #20;
            $display("\n=== HALT Instruction Detected at PC=%h===", dut.pc);
            $display("\n=== All Registers (Hex/Dec) ===");
            $display("R0 = %04h (%5d)    R1 = %04h (%5d)", 
                     dut.u_rf.regs[0], dut.u_rf.regs[0],
                     dut.u_rf.regs[1], dut.u_rf.regs[1]);
            $display("R2 = %04h (%5d)    R3 = %04h (%5d)", 
                     dut.u_rf.regs[2], dut.u_rf.regs[2],
                     dut.u_rf.regs[3], dut.u_rf.regs[3]);
            $display("R4 = %04h (%5d)    R5 = %04h (%5d)", 
                     dut.u_rf.regs[4], dut.u_rf.regs[4],
                     dut.u_rf.regs[5], $signed(dut.u_rf.regs[5]));
            $display("R6 = %04h (%5d)    R7 = %04h (%5d)", 
                     dut.u_rf.regs[6], dut.u_rf.regs[6],
                     dut.u_rf.regs[7], dut.u_rf.regs[7]);
            $display("R8 = %04h (%5d)    R9 = %04h (%5d)", 
                     dut.u_rf.regs[8], dut.u_rf.regs[8],
                     dut.u_rf.regs[9], dut.u_rf.regs[9]);
            $display("RA = %04h (%5d)    RB = %04h (%5d)", 
                     dut.u_rf.regs[10], dut.u_rf.regs[10],
                     dut.u_rf.regs[11], dut.u_rf.regs[11]);
            $display("RC = %04h (%5d)    RD = %04h (%5d)", 
                     dut.u_rf.regs[12], dut.u_rf.regs[12],
                     dut.u_rf.regs[13], dut.u_rf.regs[13]);
            $display("RE = %04h (%5d)    RF = %04h (%5d)", 
                     dut.u_rf.regs[14], dut.u_rf.regs[14],
                     dut.u_rf.regs[15], dut.u_rf.regs[15]);
            #10;
            $finish;
        end
    end
endmodule

architecture/cpu_tb.vcd
$date
	Sun Dec 14 23:17:49 2025
$end
$version
	Icarus Verilog
$end
$timescale
	1ns
$end
$scope module cpu_tb $end
$var reg 1 ! clk $end
$var reg 1 " rst $end
$scope module dut $end
$var wire 1 ! clk $end
$var wire 1 " rst $end
$var wire 1 # zero $end
$var wire 16 $ write_back_data [15:0] $end
$var wire 4 % rs2_sel [3:0] $end
$var wire 16 & rs2_data [15:0] $end
$var wire 4 ' rs1_sel [3:0] $end
$var wire 16 ( rs1_data [15:0] $end
$var wire 1 ) reg_write $end
$var wire 4 * rd_sel [3:0] $end
$var wire 8 + pc [7:0] $end
$var wire 8 , next_pc [7:0] $end
$var wire 1 - mem_write $end
$var wire 1 . mem_to_reg $end
$var wire 16 / mem_read_data [15:0] $end
$var wire 1 0 mem_read $end
$var wire 16 1 instr [15:0] $end
$var wire 1 2 alu_src $end
$var wire 16 3 alu_result [15:0] $end
$var wire 4 4 alu_op [3:0] $end
$var wire 16 5 alu_b [15:0] $end
$scope module alu0 $end
$var wire 16 6 b [15:0] $end
$var wire 1 # zero $end
$var wire 4 7 alu_control [3:0] $end
$var wire 16 8 a [15:0] $end
$var reg 16 9 alu_result [15:0] $end
$upscope $end
$scope module cu $end
$var wire 4 : opcode [3:0] $end
$var reg 4 ; alu_op [3:0] $end
$var reg 1 2 alu_src $end
$var reg 1 0 mem_read $end
$var reg 1 . mem_to_reg $end
$var reg 1 - mem_write $end
$var reg 1 ) reg_write $end
$upscope $end
$scope module dmem0 $end
$var wire 8 < addr [7:0] $end
$var wire 1 ! clk $end
$var wire 1 0 mem_read $end
$var wire 1 - mem_write $end
$var wire 16 = write_data [15:0] $end
$var wire 16 > read_data [15:0] $end
$var integer 32 ? i [31:0] $end
$upscope $end
$scope module imem0 $end
$var wire 16 @ instr [15:0] $end
$var wire 8 A addr [7:0] $end
$var integer 32 B i [31:0] $end
$upscope $end
$scope module pc0 $end
$var wire 1 ! clk $end
$var wire 8 C next_pc [7:0] $end
$var wire 1 " rst $end
$var reg 8 D pc [7:0] $end
$upscope $end
$scope module rf $end
$var wire 1 ! clk $end
$var wire 4 E rd [3:0] $end
$var wire 16 F rd_data [15:0] $end
$var wire 1 ) reg_write $end
$var wire 4 G rs1 [3:0] $end
$var wire 16 H rs1_data [15:0] $end
$var wire 4 I rs2 [3:0] $end
$var wire 16 J rs2_data [15:0] $end
$var wire 1 " rst $end
$var integer 32 K i [31:0] $end
$upscope $end
$upscope $end
$upscope $end
$enddefinitions $end
$comment Show the parameter values. $end
$dumpall
$end
#0
$dumpvars
b10000 K
b0 J
b0 I
b0 H
b0 G
b11 F
b1 E
b0 D
b1 C
b100000000 B
b0 A
b110000100000011 @
b100000000 ?
b0 >
b0 =
b11 <
b0 ;
b110 :
b11 9
b0 8
b0 7
b11 6
b11 5
b0 4
b11 3
12
b110000100000011 1
00
b0 /
0.
0-
b1 ,
b0 +
b1 *
1)
b0 (
b0 '
b0 &
b0 %
b11 $
0#
1"
0!
$end
#5
b10000 K
1!
#10
0!
#15
b111 $
b111 F
b111 <
b111 3
b111 9
b111 5
b111 6
b10 *
b10 E
b110001000000111 1
b110001000000111 @
b10 ,
b10 C
b1 +
b1 A
b1 D
1!
0"
#20
0!
#25
b11 '
b11 G
b0 $
b0 F
b0 <
1#
b0 3
b0 9
b0 5
b0 6
b101 4
b101 7
b101 ;
02
1)
b1010 *
b1010 E
b101 :
b101001100001010 1
b101001100001010 @
b11 ,
b11 C
b10 +
b10 A
b10 D
1!
#30
0!
#35
b1 $
b1 F
b1 <
0#
b1 3
b1 9
b1 *
b1 E
b111 5
b111 6
b111 &
b111 =
b111 J
b10 %
b10 I
b101001100100001 1
b101001100100001 @
b100 ,
b100 C
b11 +
b11 A
b11 D
1!
#40
0!
#45
b0 '
b0 G
b1111 $
b1111 F
b1111 <
0#
b1111 3
b1111 9
12
b0 4
b0 7
b0 ;
1)
b11 *
b11 E
b1111 5
b1111 6
b110 :
b0 &
b0 =
b0 J
b0 %
b0 I
b110001100001111 1
b110001100001111 @
b101 ,
b101 C
b100 +
b100 A
b100 D
1!
#50
0!
#55
b0 $
b0 F
b0 <
1#
b0 3
b0 9
b0 5
b0 6
b101 4
b101 7
b101 ;
02
1)
b11 *
b11 E
b101 '
b101 G
b101 :
b100 %
b100 I
b101010101000011 1
b101010101000011 @
b110 ,
b110 C
b101 +
b101 A
b101 D
1!
#60
0!
#65
b0 4
b0 7
b0 ;
1)
b0 *
b0 E
b0 '
b0 G
b0 :
b0 %
b0 I
b0 1
b0 @
b111 ,
b111 C
b110 +
b110 A
b110 D
1!
#70
0!
#75
b1000 ,
b1000 C
b111 +
b111 A
b111 D
1!
#80
0!
#85
b1001 ,
b1001 C
b1000 +
b1000 A
b1000 D
1!
#90
0!
#95
b1010 ,
b1010 C
b1001 +
b1001 A
b1001 D
1!
#100
0!
#105
b1011 ,
b1011 C
b1010 +
b1010 A
b1010 D
1!
#110
0!
#115
b1100 ,
b1100 C
b1011 +
b1011 A
b1011 D
1!
#120
0!
#125
b1101 ,
b1101 C
b1100 +
b1100 A
b1100 D
1!
#130
0!
#135
b1110 ,
b1110 C
b1101 +
b1101 A
b1101 D
1!
#140
0!
#145
b1111 ,
b1111 C
b1110 +
b1110 A
b1110 D
1!
#150
0!
#155
b10000 ,
b10000 C
b1111 +
b1111 A
b1111 D
1!
